README.rst
setup.py
torqsubmit/__init__.py
torqsubmit/_misc.py
torqsubmit/_submit.py
torqsubmit/_test.py
torqsubmit/store.py
torqsubmit/torque_executor.py
torqsubmit/torque_wrapper.py
torque_submit.egg-info/PKG-INFO
torque_submit.egg-info/SOURCES.txt
torque_submit.egg-info/dependency_links.txt
torque_submit.egg-info/top_level.txt