Metadata-Version: 1.1
Name: torque-submit
Version: 0.0.3
Summary: Python script to submit torque jobs in a very hackish way
Home-page: https://github.com/jbzdak/torque-submitter
Author: Jacek Bzdak
Author-email: jbzdak@gmail.com
License: Apache 2.0
Platform: UNKNOWN
Classifier: Development Status :: 4 - Beta
Classifier: Intended Audience :: Developers
Classifier: License :: OSI Approved :: Apache Software License
Classifier: Programming Language :: Python :: 2.7
Classifier: Programming Language :: Python :: 3.4
